pytest_cleanup/__init__.py
pytest_cleanup/__main__.py
pytest_cleanup/common.py
pytest_cleanup/constants.py
pytest_cleanup/recorder.py
pytest_cleanup/runtime.py
pytest_cleanup-0.4.dist-info/WHEEL
pytest_cleanup-0.4.dist-info/METADATA
pytest_cleanup-0.4.dist-info/RECORD
