Metadata-Version: 2.1
Name: pytest_cleanup
Version: 0.4
Summary: Automated, comprehensive and well-organised pytest test cases.
Home-page: https://github.com/jeshan/pytest-cleanup
License: UNKNOWN
Author: Jeshan G. BABOOA
Author-email: j@jeshan.co
Classifier: License :: OSI Approved :: MIT License
Requires-Dist: dill <1
Requires-Dist: jsonpickle <2
Requires-Dist: loguru <1
